LICENSE.txt
MANIFEST.in
README.md
requirements.txt
setup.py
fs_walker/__init__.py
fs_walker/api.py
fs_walker/duplicate.py
fs_walker/missing.py
fs_walker/walker.py
fs_walker.egg-info/PKG-INFO
fs_walker.egg-info/SOURCES.txt
fs_walker.egg-info/dependency_links.txt
fs_walker.egg-info/entry_points.txt
fs_walker.egg-info/requires.txt
fs_walker.egg-info/top_level.txt