Metadata-Version: 2.1
Name: fs-walker
Version: 0.0.1
Summary: Walk your file system to check duplicate or missing files
Home-page: https://github.com/hoduche/fs-walker
Author: Henri-Olivier Duché
Author-email: hoduche@yahoo.fr
License: MIT
Download-URL: https://github.com/hoduche/fs-walker/archive/v0.0.1.tar.gz
Keywords: fs filesystem file system walk crawl files duplicate missing
Platform: UNKNOWN
Classifier: Programming Language :: Python :: 3
Classifier: License :: OSI Approved :: MIT License
Classifier: Operating System :: OS Independent
Requires-Python: >=3.7
